solidpython_reloader-0.1.4.data/scripts/sp-reloader
spreloader/__init__.py
spreloader/command_line.py
spreloader/spreloader.py
solidpython_reloader-0.1.4.dist-info/LICENSE
solidpython_reloader-0.1.4.dist-info/METADATA
solidpython_reloader-0.1.4.dist-info/WHEEL
solidpython_reloader-0.1.4.dist-info/entry_points.txt
solidpython_reloader-0.1.4.dist-info/top_level.txt
solidpython_reloader-0.1.4.dist-info/RECORD
