Metadata-Version: 2.1
Name: solidpython-reloader
Version: 0.1.4
Summary: Automatically reload solidpython file on change.
Home-page: https://github.com/Fortschritt/solidpython-reloader
Author: Mattes Sarcander
License: UNKNOWN
Keywords: solidpython
Platform: UNKNOWN
Classifier: Development Status :: 4 - Beta
Classifier: Programming Language :: Python :: 3
Requires-Python: >=3.5
Requires-Dist: Django (<2.3,>=2.2)
Requires-Dist: solidpython
